interceptor/__init__.py
interceptor/config.py
interceptor/intercepting.py
interceptor/run.py
interceptor/whereis.py
interceptor/templates/cmdline.py
interceptor/templates/config
cmd_interceptor-2.1.dist-info/LICENSE
cmd_interceptor-2.1.dist-info/METADATA
cmd_interceptor-2.1.dist-info/WHEEL
cmd_interceptor-2.1.dist-info/entry_points.txt
cmd_interceptor-2.1.dist-info/top_level.txt
cmd_interceptor-2.1.dist-info/RECORD
