Metadata-Version: 2.1
Name: cmd-interceptor
Version: 2.1
Summary: A tool to intercept calls to other tools and alter their arguments
Home-page: https://github.com/Dronehub/interceptor
Author: Piotr Maślanka
Author-email: piotr.maslanka@dronehub.ai
License: UNKNOWN
Project-URL: Code, https://github.com/Dronehub/interceptor
Project-URL: Issue tracker, https://github.com/Dronehub/interceptor/issues
Keywords: command line,cmdline,intercept,arguments,args
Platform: UNKNOWN
Classifier: Programming Language :: Python
Classifier: Programming Language :: Python :: 3.5
Classifier: Programming Language :: Python :: 3.6
Classifier: Programming Language :: Python :: 3.7
Classifier: Programming Language :: Python :: 3.8
Classifier: Programming Language :: Python :: 3.9
Classifier: Programming Language :: Python :: Implementation :: CPython
Classifier: Programming Language :: Python :: Implementation :: PyPy
Classifier: Operating System :: POSIX
Classifier: Development Status :: 5 - Production/Stable
Classifier: License :: OSI Approved :: MIT License
Requires-Python: !=2.7.*,!=3.0.*,!=3.1.*,!=3.2.*
Requires-Dist: satella
